README.md
setup.cfg
setup.py
ApiWrap.egg-info/PKG-INFO
ApiWrap.egg-info/SOURCES.txt
ApiWrap.egg-info/dependency_links.txt
ApiWrap.egg-info/requires.txt
ApiWrap.egg-info/top_level.txt
wrapit/__init__.py
wrapit/api_wrapper.py