Metadata-Version: 1.1
Name: ApiWrap
Version: 0.1.1
Summary: A simple HTTP POST API wrapper for Python classes
Home-page: https://github.com/gamihaila/ApiWrap
Author: George A. Mihaila
Author-email: george.mihaila@gmail.com
License: MIT
Download-URL: https://github.com/gamihaila/ApiWrap/archive/0.1.1.tar.gz
Platform: UNKNOWN
Classifier: Development Status :: 3 - Alpha
Classifier: Intended Audience :: Developers
Classifier: Topic :: Software Development :: Build Tools
Classifier: License :: OSI Approved :: MIT License
Classifier: Programming Language :: Python :: 3.4
